Thread_Flask_Prometheus-0.0.3.dist-info/DESCRIPTION.rst
Thread_Flask_Prometheus-0.0.3.dist-info/METADATA
Thread_Flask_Prometheus-0.0.3.dist-info/RECORD
Thread_Flask_Prometheus-0.0.3.dist-info/WHEEL
Thread_Flask_Prometheus-0.0.3.dist-info/metadata.json
Thread_Flask_Prometheus-0.0.3.dist-info/top_level.txt
flask_prometheus/__init__.py
