Metadata-Version: 2.0
Name: Thread-Flask-Prometheus
Version: 0.0.3
Summary: Prometheus client instrumentation for flask.
Home-page: http://github.com/thread/thread-flask-prometheus
Author: Shane Barratt
Author-email: stbarratt@gmail.com
License: BSD
Keywords: prometheus monitoring
Platform: any
Classifier: Intended Audience :: Developers
Classifier: Development Status :: 3 - Alpha
Classifier: License :: OSI Approved :: BSD License
Classifier: Operating System :: OS Independent
Classifier: Environment :: Web Environment
Classifier: Topic :: System :: Monitoring
Classifier: Topic :: Internet :: WWW/HTTP :: Dynamic Content
Classifier: Topic :: Software Development :: Libraries :: Python Modules
Classifier: Programming Language :: Python
Classifier: Programming Language :: Python :: 2
Classifier: Programming Language :: Python :: 2.6
Classifier: Programming Language :: Python :: 2.7
Classifier: Programming Language :: Python :: 3
Classifier: Programming Language :: Python :: 3.3
Classifier: Programming Language :: Python :: 3.4
Classifier: Programming Language :: Python :: 3.5
Requires-Dist: Flask (>=0.10)
Requires-Dist: prometheus-client (>=0.0.14)
